PSTansformer/__init__.py
PSTansformer/config.py
PSTansformer/dataset.py
PSTansformer/model.py
PSTansformer/train.py
diffusion/__init__.py
diffusion/attention.py
diffusion/clip.py
diffusion/ddpm.py
diffusion/decoder.py
diffusion/diffusion.py
diffusion/encoder.py
diffusion/model_converter.py
diffusion/model_loader.py
diffusion/pipeline.py
PSTransformer-2.3.0.dist-info/LICENSE
PSTransformer-2.3.0.dist-info/METADATA
PSTransformer-2.3.0.dist-info/WHEEL
PSTransformer-2.3.0.dist-info/top_level.txt
PSTransformer-2.3.0.dist-info/RECORD
