Metadata-Version: 2.1
Name: PSTransformer
Version: 2.3.0
Summary: `PSTransformer` is a Python package that provides two high-level features.
Author: https://github.com/ProgramerSalar
Author-email: <manishkumar60708090@gmail.com>
Keywords: python,transformer,chat-GPT Transformer
Classifier: Development Status :: 1 - Planning
Classifier: Intended Audience :: Developers
Classifier: Programming Language :: Python :: 3
Classifier: Operating System :: Unix
Classifier: Operating System :: MacOS :: MacOS X
Classifier: Operating System :: Microsoft :: Windows
License-File: LICENSE
Requires-Dist: torch
Requires-Dist: tqdm
Requires-Dist: datasets
Requires-Dist: tokenizers
Requires-Dist: tensorboard
